{
	"ID": 347,
	"name": "VACODYM_890AP_150C",
	"conductivity": 0.0,
	"relPermeability": 0.0,
	"remanence": "no information",
	"BHCurve_type": "NL",
	"B": [
		0.0,
		0.0126631,
		0.0262845,
		0.0399059,
		0.0535273,
		0.0671487,
		0.0807701,
		0.0943914,
		0.108013,
		0.121634,
		0.135256,
		0.148877,
		0.162498,
		0.17612,
		0.189741,
		0.203363,
		0.216984,
		0.230605,
		0.244227,
		0.257848,
		0.271469,
		0.285091,
		0.298712,
		0.312334,
		0.325955,
		0.339576,
		0.353198,
		0.366819,
		0.380441,
		0.394062,
		0.407683,
		0.421305,
		0.434926,
		0.448547,
		0.462169,
		0.47579,
		0.489412,
		0.503033,
		0.516654,
		0.530276,
		0.543897,
		0.557518,
		0.57114,
		0.584761,
		0.598383,
		0.612004,
		0.625625,
		0.639247,
		0.652868,
		0.66649,
		0.680111,
		0.693732,
		0.707354,
		0.720975,
		0.734596,
		0.748218,
		0.761839,
		0.775461,
		0.789082,
		0.802703,
		0.816325,
		0.829946,
		0.843568,
		0.857189,
		0.87081,
		0.884432,
		0.898053,
		0.911674,
		0.925296,
		0.938917,
		0.952539,
		0.96616
	],
	"H": [
		-0.7092970000000001,
		-0.7,
		-0.69,
		-0.68,
		-0.67,
		-0.66,
		-0.65,
		-0.64,
		-0.63,
		-0.62,
		-0.61,
		-0.6,
		-0.59,
		-0.58,
		-0.57,
		-0.56,
		-0.55,
		-0.54,
		-0.53,
		-0.52,
		-0.51,
		-0.5,
		-0.49,
		-0.48,
		-0.47,
		-0.46,
		-0.45,
		-0.44,
		-0.43,
		-0.42,
		-0.41,
		-0.4,
		-0.39,
		-0.38,
		-0.37,
		-0.36,
		-0.35,
		-0.34,
		-0.33,
		-0.32,
		-0.31,
		-0.3,
		-0.29,
		-0.28,
		-0.27,
		-0.26,
		-0.25,
		-0.24,
		-0.23,
		-0.22,
		-0.21,
		-0.2,
		-0.19,
		-0.18,
		-0.17,
		-0.16,
		-0.15,
		-0.14,
		-0.13,
		-0.12,
		-0.11,
		-0.1,
		-0.09,
		-0.08,
		-0.07,
		-0.06,
		-0.05,
		-0.04,
		-0.03,
		-0.02,
		-0.01,
		0.0
	],
	"Temp": [
		"no information",
		"no information",
		"no information",
		"no information",
		"no information",
		"no information",
		"no information",
		"no information",
		"no information",
		"no information",
		"no information",
		"no information",
		"no information",
		"no information",
		"no information",
		"no information",
		"no information",
		"no information",
		"no information",
		"no information",
		"no information",
		"no information",
		"no information",
		"no information",
		"no information",
		"no information",
		"no information",
		"no information",
		"no information",
		"no information",
		"no information",
		"no information",
		"no information",
		"no information",
		"no information",
		"no information",
		"no information",
		"no information",
		"no information",
		"no information",
		"no information",
		"no information",
		"no information",
		"no information",
		"no information",
		"no information",
		"no information",
		"no information",
		"no information",
		"no information",
		"no information",
		"no information",
		"no information",
		"no information",
		"no information",
		"no information",
		"no information",
		"no information",
		"no information",
		"no information",
		"no information",
		"no information",
		"no information",
		"no information",
		"no information",
		"no information",
		"no information",
		"no information",
		"no information",
		"no information",
		"no information",
		"no information"
	]
}
