{
	"ID": 303,
	"name": "VACODYM_863AP_210C",
	"conductivity": 0.0,
	"relPermeability": 0.0,
	"remanence": "no information",
	"BHCurve_type": "NL",
	"H": [
		-0.326693,
		-0.325874,
		-0.324874,
		-0.32387400000000005,
		-0.32287400000000005,
		-0.32187400000000005,
		-0.32087400000000005,
		-0.31987400000000005,
		-0.31887400000000005,
		-0.31787400000000005,
		-0.31687400000000004,
		-0.31587400000000004,
		-0.31487400000000004,
		-0.31387400000000004,
		-0.31287400000000004,
		-0.31187400000000004,
		-0.31087400000000004,
		-0.30987400000000004,
		-0.30887400000000004,
		-0.30787400000000004,
		-0.30687400000000004,
		-0.30587400000000003,
		-0.30487400000000003,
		-0.30387400000000003,
		-0.30287400000000003,
		-0.30187400000000003,
		-0.30087400000000003,
		-0.29987400000000003,
		-0.29887400000000003,
		-0.297874,
		-0.296874,
		-0.295874,
		-0.294874,
		-0.293874,
		-0.292874,
		-0.291874,
		-0.290874,
		-0.289874,
		-0.288874,
		-0.287874,
		-0.286874,
		-0.285874,
		-0.284874,
		-0.283874,
		-0.282874,
		-0.281874,
		-0.280874,
		-0.279874,
		-0.278874,
		-0.277874,
		-0.276874,
		-0.275874,
		-0.274874,
		-0.273874,
		-0.272874,
		-0.271874,
		-0.270874,
		-0.27,
		-0.26,
		-0.25,
		-0.24,
		-0.23,
		-0.22,
		-0.21,
		-0.2,
		-0.19,
		-0.18,
		-0.17,
		-0.16,
		-0.15,
		-0.14,
		-0.13,
		-0.12,
		-0.11,
		-0.1,
		-0.09,
		-0.08,
		-0.07,
		-0.06,
		-0.05,
		-0.04,
		-0.03,
		-0.02,
		-0.01,
		0.0
	],
	"B": [
		0.0,
		0.0293268,
		0.0651197,
		0.100913,
		0.136705,
		0.172498,
		0.208291,
		0.244084,
		0.279877,
		0.31567,
		0.351827,
		0.391984,
		0.424826,
		0.442762,
		0.453416,
		0.460263,
		0.466144,
		0.471336,
		0.4762,
		0.480913,
		0.48526,
		0.489011,
		0.492377,
		0.495491,
		0.498389,
		0.501108,
		0.503685,
		0.506145,
		0.508478,
		0.510698,
		0.512822,
		0.514867,
		0.51685,
		0.51879,
		0.520698,
		0.522558,
		0.524368,
		0.526129,
		0.527843,
		0.529512,
		0.531137,
		0.532721,
		0.534276,
		0.535806,
		0.537313,
		0.538798,
		0.540262,
		0.541707,
		0.543134,
		0.544545,
		0.545941,
		0.547323,
		0.548693,
		0.550052,
		0.551402,
		0.552744,
		0.554079,
		0.555241,
		0.568564,
		0.582401,
		0.596271,
		0.610142,
		0.624012,
		0.637883,
		0.651753,
		0.665624,
		0.679494,
		0.693365,
		0.707235,
		0.721105,
		0.734976,
		0.748846,
		0.762717,
		0.776587,
		0.790458,
		0.804328,
		0.818198,
		0.832069,
		0.845939,
		0.85981,
		0.87368,
		0.887551,
		0.901421,
		0.915292,
		0.929162
	],
	"Temp": [
		"no information",
		"no information",
		"no information",
		"no information",
		"no information",
		"no information",
		"no information",
		"no information",
		"no information",
		"no information",
		"no information",
		"no information",
		"no information",
		"no information",
		"no information",
		"no information",
		"no information",
		"no information",
		"no information",
		"no information",
		"no information",
		"no information",
		"no information",
		"no information",
		"no information",
		"no information",
		"no information",
		"no information",
		"no information",
		"no information",
		"no information",
		"no information",
		"no information",
		"no information",
		"no information",
		"no information",
		"no information",
		"no information",
		"no information",
		"no information",
		"no information",
		"no information",
		"no information",
		"no information",
		"no information",
		"no information",
		"no information",
		"no information",
		"no information",
		"no information",
		"no information",
		"no information",
		"no information",
		"no information",
		"no information",
		"no information",
		"no information",
		"no information",
		"no information",
		"no information",
		"no information",
		"no information",
		"no information",
		"no information",
		"no information",
		"no information",
		"no information",
		"no information",
		"no information",
		"no information",
		"no information",
		"no information",
		"no information",
		"no information",
		"no information",
		"no information",
		"no information",
		"no information",
		"no information",
		"no information",
		"no information",
		"no information",
		"no information",
		"no information",
		"no information"
	]
}
